{"NC": {"00": [{"lat": "-21.1", "city": "Akaouane", "lon": "167.4"}, {"lat": "-20.7666667", "city": "Amoa", "lon": "165.2"}, {"lat": "-20.9", "city": "Amou\u00e9ma", "lon": "165.1666667"}, {"lat": "-21.0833333", "city": "An\u00e9o", "lon": "167.4333333"}, {"lat": "-20.7", "city": "An\u00e9zitch", "lon": "167.1833333"}, {"lat": "-19.6833333", "city": "Aou\u00e9", "lon": "163.65"}, {"lat": "-21.4", "city": "Aoumou", "lon": "165.8166667"}, {"lat": "-20.2666667", "city": "Arama", "lon": "164.2"}, {"lat": "-20.45", "city": "Ashir", "lon": "166.6"}, {"lat": "-20.95", "city": "At\u00e9ou", "lon": "164.9"}, {"lat": "-21.4666667", "city": "Atha", "lon": "168.0166667"}, {"lat": "-22.2166667", "city": "Auteuil", "lon": "166.4833333"}, {"lat": "-19.6833333", "city": "Aw\u00e9", "lon": "163.65"}, {"lat": "-21.6", "city": "Awi", "lon": "167.95"}, {"lat": "-21.4666667", "city": "Azareu", "lon": "165.4666667"}, {"lat": "-20.0833333", "city": "Baaba", "lon": "163.9833333"}, {"lat": "-21.2", "city": "B\u00e2", "lon": "165.55"}, {"lat": "-20.3833333", "city": "Babouillat", "lon": "164.1333333"}, {"lat": "-21.0666667", "city": "Baco", "lon": "164.9"}, {"lat": "-21.5666667", "city": "Bakouya", "lon": "165.4833333"}, {"lat": "-20.6833333", "city": "Balaba", "lon": "166.5166667"}, {"lat": "-20.3166667", "city": "Balade", "lon": "164.5"}, {"lat": "-20.35", "city": "Balagam", "lon": "164.4"}, {"lat": "-20.35", "city": "Balagham", "lon": "164.4"}, {"lat": "-20.2833333", "city": "Balaguet", "lon": "164.25"}, {"lat": "-20.6166667", "city": "Banout", "lon": "166.5666667"}, {"lat": "-20.7", "city": "Baoui", "lon": "164.4666667"}, {"lat": "-20.2333333", "city": "Baoum", "lon": "164.3166667"}, {"lat": "-20.6833333", "city": "Bas-Coulna", "lon": "164.7833333"}, {"lat": "-21.3333333", "city": "Basse-Poya", "lon": "165.15"}, {"lat": "-20.95", "city": "Bayes", "lon": "165.4"}, {"lat": "-21.2333333", "city": "Bernheim", "lon": "165.0333333"}, {"lat": "-21.4833333", "city": "B\u00e9ts\u00e8da", "lon": "167.8666667"}, {"lat": "-22.2833333", "city": "Blanchot", "lon": "166.45"}, {"lat": "-21.5", "city": "Boakaine", "lon": "165.9333333"}, {"lat": "-20.1166667", "city": "Boara", "lon": "164.0"}, {"lat": "-20.9666667", "city": "Bobeitio", "lon": "165.0"}, {"lat": "-21.3166667", "city": "Bo\u00e9areu", "lon": "165.5666667"}, {"lat": "-21.6", "city": "Boghen", "lon": "165.5666667"}, {"lat": "-21.6", "city": "Boguen", "lon": "165.5666667"}, {"lat": "-21.3666667", "city": "Bogui", "lon": "165.4333333"}, {"lat": "-20.4333333", "city": "Bond\u00e9", "lon": "164.4333333"}, {"lat": "-21.5666667", "city": "Bon\u00e9", "lon": "168.0166667"}, {"lat": "-20.9166667", "city": "Bopope", "lon": "165.0666667"}, {"lat": "-21.3666667", "city": "Bor\u00e9ar\u00e9", "lon": "165.4666667"}, {"lat": "-20.1333333", "city": "Bouabondo", "lon": "164.0166667"}, {"lat": "-20.2666667", "city": "Bouarou", "lon": "164.2"}, {"lat": "-20.3", "city": "Boucrabat", "lon": "164.0666667"}, {"lat": "-20.5333333", "city": "Bou\u00e9las", "lon": "164.55"}, {"lat": "-20.2333333", "city": "Bou\u00e9manda", "lon": "164.0166667"}, {"lat": "-20.3", "city": "Bou\u00e9rabat", "lon": "164.0666667"}, {"lat": "-20.3", "city": "Bouerabate", "lon": "164.0666667"}, {"lat": "-21.45", "city": "Bou\u00e9r\u00e9gaou", "lon": "165.5166667"}, {"lat": "-21.45", "city": "Bouirou", "lon": "165.5333333"}, {"lat": "-21.8666667", "city": "Bouloupari", "lon": "166.05"}, {"lat": "-21.8666667", "city": "Boulouparis", "lon": "166.05"}, {"lat": "-21.5666667", "city": "Bourail", "lon": "165.4833333"}, {"lat": "-21.5666667", "city": "Boureil", "lon": "165.4833333"}, {"lat": "-20.8166667", "city": "Boyen", "lon": "164.6166667"}, {"lat": "-22.2666667", "city": "Briqueterie", "lon": "166.5666667"}, {"lat": "-20.2333333", "city": "Buemanda", "lon": "164.0166667"}, {"lat": "-20.3", "city": "Buerabat", "lon": "164.0666667"}, {"lat": "-20.4333333", "city": "Bui", "lon": "164.4"}, {"lat": "-21.8666667", "city": "Bulupari", "lon": "166.05"}, {"lat": "-20.3", "city": "Burabat", "lon": "164.0666667"}, {"lat": "-21.5666667", "city": "Burail", "lon": "165.4833333"}, {"lat": "-19.7333333", "city": "Bw\u00e9o", "lon": "163.6666667"}, {"lat": "-20.7166667", "city": "Caavatch", "lon": "164.8333333"}, {"lat": "-21.5", "city": "Camp de Nanda\u00ef", "lon": "165.45"}, {"lat": "-21.5333333", "city": "Canala", "lon": "165.95"}, {"lat": "-21.6", "city": "Cenge\u00eft\u00e9", "lon": "167.9"}, {"lat": "-21.4666667", "city": "C\u00e9ni", "lon": "168.0166667"}, {"lat": "-20.4833333", "city": "Chagrin", "lon": "164.25"}, {"lat": "-21.4833333", "city": "Cha\u00efnon", "lon": "165.8166667"}, {"lat": "-20.7833333", "city": "Ch\u00e9p\u00e9n\u00e9h\u00e9", "lon": "167.15"}, {"lat": "-20.7833333", "city": "Chepeneke", "lon": "167.15"}, {"lat": "-21.6166667", "city": "Coind\u00e9", "lon": "165.95"}, {"lat": "-20.4833333", "city": "Colnett", "lon": "164.7333333"}, {"lat": "-22.2333333", "city": "Conception", "lon": "166.5"}, {"lat": "-20.75", "city": "Congouma", "lon": "165.0833333"}, {"lat": "-21.35", "city": "Coula", "lon": "165.45"}, {"lat": "-21.3166667", "city": "Cradji", "lon": "165.15"}, {"lat": "-21.55", "city": "Cuad\u00e8ne", "lon": "168.1"}, {"lat": "-20.7", "city": "Daking", "lon": "167.1666667"}, {"lat": "-20.3666667", "city": "Diahot-Paraoua", "lon": "164.4333333"}, {"lat": "-20.4666667", "city": "Diahou\u00e9", "lon": "164.6833333"}, {"lat": "-21.0", "city": "Diakana", "lon": "164.8666667"}, {"lat": "-21.6666667", "city": "Dogny", "lon": "165.9333333"}, {"lat": "-20.7", "city": "Dokin", "lon": "167.1666667"}, {"lat": "-20.7", "city": "Doking", "lon": "167.1666667"}, {"lat": "-21.3", "city": "Don\u00e9va", "lon": "165.6"}, {"lat": "-20.9333333", "city": "Dosip", "lon": "167.35"}, {"lat": "-21.5666667", "city": "Dothio", "lon": "166.1"}, {"lat": "-21.5666667", "city": "Dothiu", "lon": "166.1"}, {"lat": "-20.9333333", "city": "Dou\u00e9oulou", "lon": "167.0833333"}, {"lat": "-22.15", "city": "Dumb\u00e9a", "lon": "166.45"}, {"lat": "-20.7833333", "city": "Eacho", "lon": "167.1333333"}, {"lat": "-21.5666667", "city": "Ema", "lon": "165.9"}, {"lat": "-21.5166667", "city": "En\u00e9n\u00e9", "lon": "168.0666667"}, {"lat": "-21.6333333", "city": "Eni", "lon": "167.95"}, {"lat": "-20.45", "city": "Eo", "lon": "166.6"}, {"lat": "-21.5166667", "city": "Et\u00e9", "lon": "167.85"}, {"lat": "-21.5", "city": "Ethi", "lon": "167.85"}, {"lat": "-20.65", "city": "Faiaou\u00e9", "lon": "166.5333333"}, {"lat": "-20.65", "city": "Faiau\u00e9", "lon": "166.5333333"}, {"lat": "-21.6666667", "city": "Farino", "lon": "165.7666667"}, {"lat": "-20.65", "city": "Fayaou\u00e9", "lon": "166.5333333"}, {"lat": "-20.7166667", "city": "Fayawa", "lon": "166.4666667"}, {"lat": "-20.9166667", "city": "Foaobanik", "lon": "164.75"}, {"lat": "-21.6833333", "city": "Fonwary", "lon": "165.7833333"}, {"lat": "-21.6833333", "city": "Fonwhary", "lon": "165.7833333"}, {"lat": "-21.7666667", "city": "For\u00eat Noire", "lon": "165.85"}, {"lat": "-21.1333333", "city": "For\u00eat Plate", "lon": "165.1166667"}, {"lat": "-22.55", "city": "Gadji", "lon": "167.4333333"}, {"lat": "-20.75", "city": "Gala", "lon": "164.8833333"}, {"lat": "-20.55", "city": "Galagaoui", "lon": "164.2666667"}, {"lat": "-20.9333333", "city": "Galil\u00e9e", "lon": "165.2666667"}, {"lat": "-20.7", "city": "Gama\u00ef", "lon": "164.4833333"}, {"lat": "-20.7", "city": "Ganem", "lon": "164.9333333"}, {"lat": "-21.5333333", "city": "G\u00e9lima", "lon": "165.9833333"}, {"lat": "-21.5166667", "city": "Ghio", "lon": "166.1"}, {"lat": "-21.9", "city": "Gilles", "lon": "166.0166667"}, {"lat": "-21.9", "city": "Gilli\u00e9s", "lon": "166.0166667"}, {"lat": "-21.1166667", "city": "Goa", "lon": "165.3"}, {"lat": "-21.2166667", "city": "Gohapin", "lon": "165.2666667"}, {"lat": "-21.2166667", "city": "Goipin", "lon": "165.2666667"}, {"lat": "-20.2666667", "city": "Golone", "lon": "164.1166667"}, {"lat": "-20.6666667", "city": "Gomen", "lon": "164.4"}, {"lat": "-20.8333333", "city": "Gomen Ouaco", "lon": "164.4666667"}, {"lat": "-21.3", "city": "Gond\u00e9", "lon": "165.4666667"}, {"lat": "-21.35", "city": "Gondon", "lon": "165.4333333"}, {"lat": "-21.35", "city": "Gondou", "lon": "165.4333333"}, {"lat": "-22.2833333", "city": "Goro", "lon": "167.0166667"}, {"lat": "-20.45", "city": "Gossanat", "lon": "166.6333333"}, {"lat": "-21.3166667", "city": "Gouaraoui", "lon": "165.5666667"}, {"lat": "-21.3", "city": "Gouareu", "lon": "165.6333333"}, {"lat": "-21.6", "city": "Gouaro", "lon": "165.4333333"}, {"lat": "-21.1", "city": "Goyetta", "lon": "165.35"}, {"lat": "-21.7333333", "city": "Grand-Borindi", "lon": "166.45"}, {"lat": "-21.6333333", "city": "Grand Gouli", "lon": "165.8166667"}, {"lat": "-21.0833333", "city": "Grochain", "lon": "165.3833333"}, {"lat": "-21.0333333", "city": "Grombaou", "lon": "164.8666667"}, {"lat": "-21.0833333", "city": "Grondu", "lon": "165.3833333"}, {"lat": "-21.6", "city": "Guaro", "lon": "165.4333333"}, {"lat": "-20.6666667", "city": "Gu\u00e9hi", "lon": "166.5333333"}, {"lat": "-21.5333333", "city": "Haouli", "lon": "165.85"}, {"lat": "-20.9333333", "city": "Hap\u00e9tra", "lon": "167.15"}, {"lat": "-20.6333333", "city": "Haut-Coulna", "lon": "164.7333333"}, {"lat": "-22.1333333", "city": "Haute Couvel\u00e9e", "lon": "166.4666667"}, {"lat": "-21.4833333", "city": "Haute Pou\u00e9o", "lon": "165.5166667"}, {"lat": "-22.05", "city": "Haute Tamoa", "lon": "166.3"}, {"lat": "-20.9", "city": "Havila", "lon": "167.25"}, {"lat": "-20.6833333", "city": "Hiengh\u00e8ne", "lon": "164.9333333"}, {"lat": "-20.6833333", "city": "Hiengherie", "lon": "164.9333333"}, {"lat": "-21.05", "city": "Hm\u00e9lek", "lon": "167.2833333"}, {"lat": "-21.45", "city": "Hnadid", "lon": "168.1"}, {"lat": "-21.4666667", "city": "Hna\u00e9n\u00e9de", "lon": "168.0"}, {"lat": "-20.9833333", "city": "Hnaeu", "lon": "167.3833333"}, {"lat": "-20.9", "city": "Hnapalou", "lon": "167.2666667"}, {"lat": "-20.9166667", "city": "Hnass\u00e9", "lon": "167.2666667"}, {"lat": "-21.4333333", "city": "Hnaway\u00e9ce", "lon": "167.8666667"}, {"lat": "-21.1833333", "city": "H\u00f4", "lon": "165.5333333"}, {"lat": "-20.9166667", "city": "Honem", "lon": "167.2833333"}, {"lat": "-21.2833333", "city": "Houa\u00eflou", "lon": "165.6166667"}, {"lat": "-20.05", "city": "Houone", "lon": "163.8"}, {"lat": "-21.0166667", "city": "Houts", "lon": "167.4"}, {"lat": "-21.2833333", "city": "Hua\u00eflu", "lon": "165.6166667"}, {"lat": "-20.7666667", "city": "Hunet\u00e9", "lon": "167.1"}, {"lat": "-22.15", "city": "Iate", "lon": "166.9"}, {"lat": "-21.0166667", "city": "Inagod", "lon": "167.3833333"}, {"lat": "-20.9333333", "city": "Ina", "lon": "165.35"}, {"lat": "-22.1333333", "city": "Juv\u00e9nat Sainte-Th\u00e9r\u00e8se", "lon": "166.3166667"}, {"lat": "-20.6666667", "city": "Kaala-Gom\u00e9n", "lon": "164.4"}, {"lat": "-21.3833333", "city": "Kab\u00e9yourou", "lon": "165.4"}, {"lat": "-21.4", "city": "Ka\u00e9watine", "lon": "167.9333333"}, {"lat": "-21.4666667", "city": "Kaewaura", "lon": "167.95"}, {"lat": "-21.5333333", "city": "Kako", "lon": "165.9"}, {"lat": "-20.8666667", "city": "Kal\u00e9dicta", "lon": "164.6833333"}, {"lat": "-21.5", "city": "Kal\u00e9ne", "lon": "167.85"}, {"lat": "-22.65", "city": "Kam\u00e9", "lon": "167.4833333"}, {"lat": "-21.35", "city": "Kamoui", "lon": "165.65"}, {"lat": "-22.625", "city": "Kana", "lon": "167.4208333"}, {"lat": "-21.5333333", "city": "Kanala", "lon": "165.95"}, {"lat": "-20.75", "city": "Kanguma", "lon": "165.0833333"}, {"lat": "-20.9", "city": "Kanono", "lon": "167.2666667"}, {"lat": "-21.2166667", "city": "Kaora", "lon": "165.5666667"}, {"lat": "-21.2833333", "city": "Kapou\u00e9", "lon": "165.6333333"}, {"lat": "-21.4", "city": "Karagreu", "lon": "165.3833333"}, {"lat": "-20.6333333", "city": "Karemb\u00e9", "lon": "164.3166667"}, {"lat": "-22.0166667", "city": "Karenga", "lon": "166.2333333"}, {"lat": "-21.4166667", "city": "Kasouri", "lon": "165.8333333"}, {"lat": "-21.5666667", "city": "Katrikoin", "lon": "165.7"}, {"lat": "-20.7166667", "city": "Kavatch", "lon": "164.8166667"}, {"lat": "-21.0333333", "city": "K\u00e9deigne", "lon": "167.2166667"}, {"lat": "-21.55", "city": "K\u00e9n\u00e9rou", "lon": "165.8833333"}, {"lat": "-22.6833333", "city": "K\u00e9r\u00e9", "lon": "167.4833333"}, {"lat": "-20.6333333", "city": "K\u00e9remb\u00e9", "lon": "164.3166667"}, {"lat": "-21.6", "city": "K\u00e9zi\u00e8n\u00e9", "lon": "167.9"}, {"lat": "-21.4333333", "city": "Kiko\u00e9", "lon": "165.5"}, {"lat": "-20.8166667", "city": "Kirinata", "lon": "167.25"}, {"lat": "-21.1166667", "city": "Kode", "lon": "167.4166667"}, {"lat": "-20.8", "city": "Ko\u00e9", "lon": "165.2666667"}, {"lat": "-21.5333333", "city": "Koh", "lon": "165.8333333"}, {"lat": "-21.6166667", "city": "Koind\u00e9", "lon": "165.95"}, {"lat": "-20.85", "city": "Kokengone", "lon": "165.25"}, {"lat": "-20.85", "city": "Kokingon\u00e9", "lon": "165.25"}, {"lat": "-20.6833333", "city": "Koligoh-Gomen", "lon": "164.4666667"}, {"lat": "-20.6833333", "city": "Koligoh", "lon": "164.4666667"}, {"lat": "-21.0666667", "city": "Kon\u00e9", "lon": "164.8666667"}, {"lat": "-20.75", "city": "Kongouma", "lon": "165.0833333"}, {"lat": "-21.0333333", "city": "Koniambo", "lon": "164.8666667"}, {"lat": "-20.6", "city": "Konio", "lon": "164.4"}, {"lat": "-21.5", "city": "Kono\u00e9-Chaou\u00e9", "lon": "165.7"}, {"lat": "-20.6833333", "city": "Koout", "lon": "164.9666667"}, {"lat": "-21.5666667", "city": "Kop\u00e9lia", "lon": "166.0166667"}, {"lat": "-21.3333333", "city": "Koua", "lon": "165.7666667"}, {"lat": "-21.4333333", "city": "Kouaoua", "lon": "165.8166667"}, {"lat": "-21.6666667", "city": "Kouar\u00e9", "lon": "166.0666667"}, {"lat": "-21.7333333", "city": "Kouarga", "lon": "166.0666667"}, {"lat": "-20.6833333", "city": "Koulnou\u00e9", "lon": "164.9833333"}, {"lat": "-20.5666667", "city": "Koumac", "lon": "164.2833333"}, {"lat": "-20.5333333", "city": "Koum", "lon": "164.3333333"}, {"lat": "-20.7833333", "city": "Koumo", "lon": "167.2333333"}, {"lat": "-22.2166667", "city": "Koutio-Kou\u00e9ta", "lon": "166.4666667"}, {"lat": "-21.3333333", "city": "Kua", "lon": "165.7666667"}, {"lat": "-21.4333333", "city": "Kuaua", "lon": "165.8166667"}, {"lat": "-21.7833333", "city": "Kuen Tchio", "lon": "166.0833333"}, {"lat": "-21.7833333", "city": "Kuenthio", "lon": "166.0833333"}, {"lat": "-21.5333333", "city": "Kuin\u00e9", "lon": "165.9666667"}, {"lat": "-20.5666667", "city": "Kumac", "lon": "164.2833333"}, {"lat": "-20.5666667", "city": "Kumak", "lon": "164.2833333"}, {"lat": "-21.6", "city": "Kurin", "lon": "168.1166667"}, {"lat": "-22.6666667", "city": "Kuto", "lon": "167.4333333"}, {"lat": "-20.5", "city": "La Bouverie", "lon": "164.2666667"}, {"lat": "-22.2333333", "city": "La Conception", "lon": "166.5"}, {"lat": "-22.2333333", "city": "La Coul\u00e9e", "lon": "166.5666667"}, {"lat": "-22.15", "city": "La Couvel\u00e9e", "lon": "166.4666667"}, {"lat": "-21.7166667", "city": "La Foa", "lon": "165.8166667"}, {"lat": "-21.6666667", "city": "La M\u00e9douya", "lon": "165.6833333"}, {"lat": "-21.6833333", "city": "La R\u00e9sidence", "lon": "165.6833333"}, {"lat": "-21.4666667", "city": "La Roche", "lon": "168.0333333"}, {"lat": "-21.9666667", "city": "La Tarodi\u00e8re", "lon": "166.1666667"}, {"lat": "-20.35", "city": "Le Caillou", "lon": "164.4333333"}, {"lat": "-20.4833333", "city": "Le Cresson", "lon": "164.3"}, {"lat": "-20.3666667", "city": "Le Diahot", "lon": "164.4333333"}, {"lat": "-21.6", "city": "Le Gab\u00e9", "lon": "165.45"}, {"lat": "-20.7", "city": "Lekia", "lon": "166.5"}, {"lat": "-20.7", "city": "L\u00e9kine", "lon": "166.5"}, {"lat": "-20.7", "city": "Lekin", "lon": "166.5"}, {"lat": "-20.5833333", "city": "Les Charmes", "lon": "164.4166667"}, {"lat": "-22.2833333", "city": "Les Pirogues", "lon": "166.6833333"}, {"lat": "-21.4666667", "city": "Limite", "lon": "167.95"}, {"lat": "-20.6833333", "city": "Lind\u00e9ralique", "lon": "164.9666667"}, {"lat": "-21.4833333", "city": "Lion", "lon": "167.9333333"}, {"lat": "-21.0333333", "city": "Loangani", "lon": "167.4166667"}, {"lat": "-21.4833333", "city": "Lo", "lon": "167.8333333"}, {"lat": "-21.3833333", "city": "Lot", "lon": "167.85"}, {"lat": "-20.95", "city": "Loun\u00e9ou", "lon": "167.3666667"}, {"lat": "-20.9", "city": "Lu\u00e9cilla", "lon": "167.2666667"}, {"lat": "-21.0333333", "city": "Luengoni", "lon": "167.4166667"}, {"lat": "-20.2333333", "city": "Mahamat\u00e9", "lon": "164.3166667"}, {"lat": "-20.7333333", "city": "Ma\u00efna", "lon": "165.05"}, {"lat": "-20.3", "city": "Malabou", "lon": "164.1166667"}, {"lat": "-20.3333333", "city": "Malhec", "lon": "164.1833333"}, {"lat": "-22.0666667", "city": "Mami\u00e9", "lon": "166.9"}, {"lat": "-21.2833333", "city": "Man\u00e9ko", "lon": "165.5833333"}, {"lat": "-21.0666667", "city": "Mangou", "lon": "165.4166667"}, {"lat": "-20.4", "city": "Manguine", "lon": "164.4166667"}, {"lat": "-21.4666667", "city": "M\u00e9a", "lon": "165.7833333"}, {"lat": "-21.4666667", "city": "M\u00e9a-M\u00e9bara", "lon": "165.7833333"}, {"lat": "-21.7333333", "city": "M\u00e9ar\u00e9", "lon": "165.8333333"}, {"lat": "-21.3", "city": "Meareu", "lon": "165.5833333"}, {"lat": "-21.5166667", "city": "Mebuet", "lon": "167.85"}, {"lat": "-21.5", "city": "M\u00e9chin", "lon": "165.7333333"}, {"lat": "-21.3", "city": "M\u00e9daouya", "lon": "165.5166667"}, {"lat": "-21.6166667", "city": "M\u00e9du", "lon": "167.95"}, {"lat": "-21.5166667", "city": "M\u00e9hou\u00e9", "lon": "165.95"}, {"lat": "-21.3166667", "city": "M\u00e9", "lon": "165.5666667"}, {"lat": "-21.45", "city": "M\u00e9naku", "lon": "167.9666667"}, {"lat": "-21.5166667", "city": "M\u00e9n\u00e9r\u00e9m\u00e9", "lon": "165.9333333"}, {"lat": "-21.2333333", "city": "M\u00e9omo", "lon": "165.6"}, {"lat": "-21.3166667", "city": "M\u00e9oui", "lon": "165.65"}, {"lat": "-21.6333333", "city": "Messadiu", "lon": "165.5333333"}, {"lat": "-21.1833333", "city": "M\u00e9vegon", "lon": "165.5666667"}, {"lat": "-21.55", "city": "Mia", "lon": "165.9833333"}, {"lat": "-21.4833333", "city": "Miramas", "lon": "167.9833333"}, {"lat": "-21.4166667", "city": "Moindah", "lon": "165.2333333"}, {"lat": "-21.7", "city": "Moindou", "lon": "165.6833333"}, {"lat": "-21.7", "city": "Moindu", "lon": "165.6833333"}, {"lat": "-21.6666667", "city": "Mom\u00e9a", "lon": "165.6333333"}, {"lat": "-21.15", "city": "Mon\u00e9o", "lon": "165.4833333"}, {"lat": "-22.2833333", "city": "Mont-Dore", "lon": "166.5833333"}, {"lat": "-21.2666667", "city": "Montfaou\u00e9", "lon": "165.3"}, {"lat": "-19.6", "city": "Mouane", "lon": "163.6"}, {"lat": "-20.7333333", "city": "Mouly", "lon": "166.4333333"}, {"lat": "-21.1", "city": "Mou", "lon": "165.4333333"}, {"lat": "-21.7", "city": "Muendu", "lon": "165.6833333"}, {"lat": "-21.3", "city": "Mu\u00e9o", "lon": "165.0166667"}, {"lat": "-20.7333333", "city": "Muli", "lon": "166.4333333"}, {"lat": "-21.1", "city": "Mu", "lon": "165.4333333"}, {"lat": "-20.7333333", "city": "Mutchaweng", "lon": "167.1666667"}, {"lat": "-21.1", "city": "Nada", "lon": "167.4"}, {"lat": "-22.1666667", "city": "Na\u00efa", "lon": "166.25"}, {"lat": "-21.55", "city": "Nak\u00e9ty", "lon": "166.0333333"}, {"lat": "-22.1666667", "city": "Nakutakoin", "lon": "166.4166667"}, {"lat": "-21.0333333", "city": "Namamate", "lon": "167.4166667"}, {"lat": "-21.1", "city": "Nam\u00e9lagat", "lon": "167.35"}, {"lat": "-20.65", "city": "Nam\u00e9m\u00e9hu", "lon": "166.55"}, {"lat": "-20.7666667", "city": "Nanawa", "lon": "167.1"}, {"lat": "-20.7", "city": "Nan\u00e9m\u00fchata", "lon": "167.2166667"}, {"lat": "-20.8166667", "city": "Nang", "lon": "167.2333333"}, {"lat": "-22.1333333", "city": "Naniouni", "lon": "166.2833333"}, {"lat": "-21.5666667", "city": "Nanon", "lon": "165.8833333"}, {"lat": "-20.9666667", "city": "Napo\u00e9mien", "lon": "165.35"}, {"lat": "-21.5333333", "city": "Napol\u00e9onville", "lon": "165.95"}, {"lat": "-22.0833333", "city": "Nassandou", "lon": "166.25"}, {"lat": "-21.8", "city": "Nassirah", "lon": "166.0666667"}, {"lat": "-21.0666667", "city": "Nata\u00e9", "lon": "167.4333333"}, {"lat": "-20.7166667", "city": "Natchaom", "lon": "167.2166667"}, {"lat": "-20.7833333", "city": "Nathalo", "lon": "167.2666667"}, {"lat": "-21.05", "city": "Nato", "lon": "165.3666667"}, {"lat": "-21.05", "city": "Nato N\u00e9pia", "lon": "165.3666667"}, {"lat": "-22.15", "city": "Nd\u00e9", "lon": "166.3"}, {"lat": "-22.4666667", "city": "Ndji", "lon": "166.7833333"}, {"lat": "-20.9833333", "city": "N\u00e9ami", "lon": "164.9666667"}, {"lat": "-21.3333333", "city": "N\u00e9aoua", "lon": "165.65"}, {"lat": "-21.2666667", "city": "N\u00e9aria", "lon": "165.6"}, {"lat": "-21.1666667", "city": "N\u00e9avin", "lon": "165.4833333"}, {"lat": "-21.1", "city": "N\u00e9bou\u00e9ba", "lon": "165.3"}, {"lat": "-21.4833333", "city": "N\u00e9c\u00e9", "lon": "167.85"}, {"lat": "-21.2666667", "city": "N\u00e9diouen", "lon": "165.6166667"}, {"lat": "-21.3", "city": "N\u00e9divin", "lon": "165.5666667"}, {"lat": "-21.5333333", "city": "N\u00e9gropo", "lon": "165.9"}, {"lat": "-21.3", "city": "N\u00e9klia\u00ef", "lon": "165.1833333"}, {"lat": "-21.2666667", "city": "N\u00e9kou\u00e9", "lon": "165.6"}, {"lat": "-21.5166667", "city": "N\u00e9m\u00e9ara", "lon": "165.4666667"}, {"lat": "-21.5333333", "city": "N\u00e9mengui", "lon": "165.95"}, {"lat": "-21.4333333", "city": "N\u00e9oua", "lon": "165.6333333"}, {"lat": "-21.2833333", "city": "N\u00e9ouio", "lon": "165.6333333"}, {"lat": "-21.0666667", "city": "N\u00e9outa", "lon": "165.3833333"}, {"lat": "-21.0666667", "city": "N\u00e9outy", "lon": "165.3833333"}, {"lat": "-21.35", "city": "N\u00e9poui", "lon": "165.0"}, {"lat": "-21.3666667", "city": "N\u00e9pou", "lon": "165.1"}, {"lat": "-21.6166667", "city": "N\u00e9ra", "lon": "165.4833333"}, {"lat": "-21.3333333", "city": "N\u00e9rin", "lon": "165.35"}, {"lat": "-21.6333333", "city": "Nessadiou", "lon": "165.5333333"}, {"lat": "-21.2833333", "city": "Nessa Kouya", "lon": "165.5166667"}, {"lat": "-20.9666667", "city": "N\u00e9ssapou\u00e9", "lon": "165.3666667"}, {"lat": "-21.2666667", "city": "Nesson", "lon": "165.6166667"}, {"lat": "-21.0166667", "city": "Netchaot", "lon": "165.0166667"}, {"lat": "-21.4833333", "city": "Netch\u00e9", "lon": "167.85"}, {"lat": "-21.2333333", "city": "N\u00e9t\u00e9a", "lon": "165.2"}, {"lat": "-21.4833333", "city": "Netieh", "lon": "167.85"}, {"lat": "-21.0", "city": "N\u00e9vaho", "lon": "165.3666667"}, {"lat": "-21.2166667", "city": "N\u00e9ya", "lon": "165.5833333"}, {"lat": "-21.5666667", "city": "Nid\u00e9node", "lon": "167.8833333"}, {"lat": "-21.4666667", "city": "Ni\u00e9r\u00e9", "lon": "168.0833333"}, {"lat": "-21.7", "city": "Nili", "lon": "165.8166667"}, {"lat": "-20.6166667", "city": "Nimaha", "lon": "166.5666667"}, {"lat": "-21.0833333", "city": "Nimbaye", "lon": "165.3333333"}, {"lat": "-21.0833333", "city": "Nimbayes", "lon": "165.3333333"}, {"lat": "-21.3", "city": "Nindiah", "lon": "165.5833333"}, {"lat": "-21.4333333", "city": "Ni", "lon": "165.4833333"}, {"lat": "-21.6", "city": "Niri", "lon": "167.95"}, {"lat": "-21.0166667", "city": "No\u00e9li", "lon": "164.95"}, {"lat": "-20.2666667", "city": "Noet", "lon": "164.2166667"}, {"lat": "-20.1333333", "city": "Nomoudja", "lon": "164.0666667"}, {"lat": "-21.5166667", "city": "Nonhou\u00e9", "lon": "165.95"}, {"lat": "-22.2333333", "city": "Normandie", "lon": "166.4833333"}, {"lat": "-22.2666667", "city": "Noum\u00e9a", "lon": "166.45"}, {"lat": "-22.2666667", "city": "Nouville", "lon": "166.4"}, {"lat": "-22.2666667", "city": "Numea", "lon": "166.45"}, {"lat": "-20.6666667", "city": "Ognahu", "lon": "166.5666667"}, {"lat": "-20.4666667", "city": "Ognat", "lon": "166.65"}, {"lat": "-20.4333333", "city": "Ogn\u00e9", "lon": "166.6333333"}, {"lat": "-20.1", "city": "Olane", "lon": "164.05"}, {"lat": "-21.0166667", "city": "Ometteux", "lon": "165.4"}, {"lat": "-19.65", "city": "Ono", "lon": "163.6333333"}, {"lat": "-21.6833333", "city": "Onwari", "lon": "165.7833333"}, {"lat": "-21.6", "city": "Ouabao", "lon": "167.9333333"}, {"lat": "-20.8333333", "city": "Ou\u00e5co", "lon": "164.4666667"}, {"lat": "-20.6", "city": "Ouadila", "lon": "166.5666667"}, {"lat": "-20.5833333", "city": "Oua\u00e8ne", "lon": "164.6166667"}, {"lat": "-20.8833333", "city": "Ouagap", "lon": "165.2666667"}, {"lat": "-20.7333333", "city": "Ouahat", "lon": "164.7"}, {"lat": "-20.6166667", "city": "Oua\u00ef\u00e8me", "lon": "164.85"}, {"lat": "-21.3166667", "city": "Ouakaya", "lon": "165.6333333"}, {"lat": "-20.6333333", "city": "Oualanga", "lon": "164.4333333"}, {"lat": "-20.6833333", "city": "Ouamba", "lon": "164.45"}, {"lat": "-21.8", "city": "Ouam\u00e9ni", "lon": "165.9666667"}, {"lat": "-22.6", "city": "Ouam\u00e9o", "lon": "167.4333333"}, {"lat": "-22.6", "city": "Ouamoeo", "lon": "167.4333333"}, {"lat": "-20.75", "city": "Ouanache", "lon": "165.0666667"}, {"lat": "-20.6333333", "city": "Ouanane", "lon": "164.7333333"}, {"lat": "-20.5666667", "city": "Ouanap II", "lon": "164.2666667"}, {"lat": "-20.55", "city": "Ouanap I", "lon": "164.2666667"}, {"lat": "-20.7833333", "city": "Ouan Kout", "lon": "164.9833333"}, {"lat": "-20.65", "city": "Ouanpou\u00e8s", "lon": "164.9166667"}, {"lat": "-21.6166667", "city": "Oua-Ou\u00e9", "lon": "165.5833333"}, {"lat": "-20.8", "city": "Ouapan", "lon": "164.7166667"}, {"lat": "-22.4433333", "city": "Ouara", "lon": "166.8366667"}, {"lat": "-20.7166667", "city": "Ouarap", "lon": "164.9333333"}, {"lat": "-20.4", "city": "Ouarenndi", "lon": "164.45"}, {"lat": "-20.6833333", "city": "Ouar\u00e9", "lon": "164.9333333"}, {"lat": "-21.4666667", "city": "Ouass\u00e9", "lon": "166.0333333"}, {"lat": "-21.1833333", "city": "Ouat\u00e9", "lon": "165.1166667"}, {"lat": "-21.8", "city": "Oua Tom", "lon": "165.9"}, {"lat": "-20.6666667", "city": "Ouayaguette", "lon": "164.6833333"}, {"lat": "-20.4333333", "city": "Oubatche", "lon": "164.6333333"}, {"lat": "-20.6166667", "city": "Ou\u00e9bia", "lon": "164.6333333"}, {"lat": "-20.35", "city": "Ou\u00e9goa", "lon": "164.4333333"}, {"lat": "-20.7666667", "city": "Ou\u00e9 Hava", "lon": "165.0333333"}, {"lat": "-20.6", "city": "Ou\u00e9holle", "lon": "164.5333333"}, {"lat": "-20.8833333", "city": "Ou\u00e9lis", "lon": "164.6833333"}, {"lat": "-20.6", "city": "Ou\u00e9mou", "lon": "164.5666667"}, {"lat": "-21.4166667", "city": "Ou\u00e9na", "lon": "165.8166667"}, {"lat": "-20.65", "city": "Ouend\u00e9", "lon": "164.4166667"}, {"lat": "-21.3333333", "city": "Ouendji", "lon": "165.3166667"}, {"lat": "-20.5333333", "city": "Ou\u00e9n\u00e9", "lon": "164.5333333"}, {"lat": "-20.7833333", "city": "Ouengo-Pou\u00e9a\u00ef", "lon": "164.7333333"}, {"lat": "-20.7833333", "city": "Ouengo-Pou\u00e9pa\u00ef", "lon": "164.7333333"}, {"lat": "-20.6333333", "city": "Ouenguip", "lon": "164.9"}, {"lat": "-20.5166667", "city": "Ou\u00e9nia", "lon": "164.5166667"}, {"lat": "-20.65", "city": "Ouenpou\u00e8s", "lon": "164.9166667"}, {"lat": "-20.9", "city": "Ou\u00e9", "lon": "167.2666667"}, {"lat": "-21.5", "city": "Ou\u00e9roupim\u00e9", "lon": "165.7166667"}, {"lat": "-21.3166667", "city": "Ouessoin", "lon": "165.5666667"}, {"lat": "-21.9166667", "city": "Ouinan\u00e9", "lon": "166.1666667"}, {"lat": "-20.9833333", "city": "Ouindo", "lon": "165.4"}, {"lat": "-21.2833333", "city": "Ouingo", "lon": "165.5166667"}, {"lat": "-21.65", "city": "Ouipouin", "lon": "165.9666667"}, {"lat": "-21.8166667", "city": "Ouitchamba", "lon": "165.95"}, {"lat": "-20.65", "city": "Ouloup", "lon": "166.5833333"}, {"lat": "-20.05", "city": "Oumba\u00efna", "lon": "163.7833333"}, {"lat": "-20.9166667", "city": "Ounao", "lon": "165.2333333"}, {"lat": "-21.05", "city": "Oundjo", "lon": "164.7"}, {"lat": "-22.65", "city": "Ouo", "lon": "167.4166667"}, {"lat": "-22.65", "city": "Ouro", "lon": "167.4333333"}, {"lat": "-21.6", "city": "Ourou\u00e9", "lon": "166.2"}, {"lat": "-20.6666667", "city": "Ouyaguette", "lon": "164.6833333"}, {"lat": "-20.4833333", "city": "Paagoum\u00e8ne", "lon": "164.1833333"}, {"lat": "-20.4833333", "city": "Paagowmene", "lon": "164.1833333"}, {"lat": "-20.4833333", "city": "Paagumene", "lon": "164.1833333"}, {"lat": "-20.4666667", "city": "Paalo", "lon": "164.7"}, {"lat": "-20.95", "city": "Paama", "lon": "165.4"}, {"lat": "-20.3", "city": "Pabou", "lon": "164.1"}, {"lat": "-20.4833333", "city": "Pagoumene", "lon": "164.1833333"}, {"lat": "-20.55", "city": "Pagou", "lon": "164.2666667"}, {"lat": "-20.55", "city": "Paimboas", "lon": "164.55"}, {"lat": "-19.7666667", "city": "Pa\u00efrom\u00e9", "lon": "163.6833333"}, {"lat": "-22.1333333", "city": "Pa\u00efta", "lon": "166.3666667"}, {"lat": "-20.9666667", "city": "Pambou", "lon": "165.4"}, {"lat": "-20.25", "city": "Pam", "lon": "164.3"}, {"lat": "-20.9833333", "city": "Panaki", "lon": "164.8833333"}, {"lat": "-19.5833333", "city": "Panane", "lon": "163.5833333"}, {"lat": "-20.6", "city": "Pangou", "lon": "164.6333333"}, {"lat": "-20.6", "city": "Pani\u00e9", "lon": "164.8333333"}, {"lat": "-20.5333333", "city": "Panouma", "lon": "164.2833333"}, {"lat": "-20.7833333", "city": "Paola", "lon": "165.1"}, {"lat": "-20.55", "city": "Paop", "lon": "164.2666667"}, {"lat": "-21.0666667", "city": "Paouta", "lon": "165.0"}, {"lat": "-20.7833333", "city": "Papal\u00e9", "lon": "167.2666667"}, {"lat": "-21.5166667", "city": "Parahoui", "lon": "165.9833333"}, {"lat": "-20.35", "city": "Paraoua", "lon": "164.45"}, {"lat": "-21.2833333", "city": "Paraouy\u00e9", "lon": "165.65"}, {"lat": "-21.5833333", "city": "Patho", "lon": "168.1"}, {"lat": "-19.65", "city": "Pav\u00e9", "lon": "163.6333333"}, {"lat": "-21.5833333", "city": "P\u00e9d\u00e9", "lon": "167.8666667"}, {"lat": "-21.0666667", "city": "P\u00e9laoui", "lon": "164.8833333"}, {"lat": "-21.5666667", "city": "P\u00e9n\u00e9lo", "lon": "168.1"}, {"lat": "-19.5666667", "city": "Penisi", "lon": "163.6"}, {"lat": "-21.5166667", "city": "P\u00e9orawa", "lon": "168.05"}, {"lat": "-21.4166667", "city": "Perlou", "lon": "165.45"}, {"lat": "-21.8", "city": "Petit-Borindi", "lon": "166.4833333"}, {"lat": "-21.65", "city": "Petit Gouli", "lon": "165.8333333"}, {"lat": "-21.1666667", "city": "Petit Mon\u00e9", "lon": "165.5666667"}, {"lat": "-20.2333333", "city": "Peum", "lon": "164.0166667"}, {"lat": "-21.55", "city": "P\u00e9wa\u00e9t\u00e9", "lon": "168.0666667"}, {"lat": "-21.45", "city": "P\u00e9y\u00e9c\u00e9", "lon": "167.9833333"}, {"lat": "-21.7166667", "city": "Pierra", "lon": "165.8666667"}, {"lat": "-21.7166667", "city": "Pierrat", "lon": "165.8666667"}, {"lat": "-21.1", "city": "Pilmango", "lon": "167.4166667"}, {"lat": "-20.7", "city": "Pindache", "lon": "165.0"}, {"lat": "-21.05", "city": "Pinjen", "lon": "164.7666667"}, {"lat": "-22.1", "city": "Plaine aux Cailloux", "lon": "166.3666667"}, {"lat": "-22.3", "city": "Plum", "lon": "166.6666667"}, {"lat": "-21.7", "city": "Pocquereux", "lon": "165.9166667"}, {"lat": "-21.35", "city": "Po\u00ebt", "lon": "165.6"}, {"lat": "-21.0333333", "city": "Poinda", "lon": "164.9666667"}, {"lat": "-20.9333333", "city": "Poindimi\u00e9", "lon": "165.3333333"}, {"lat": "-20.8833333", "city": "Pomb\u00e9\u00ef", "lon": "165.1833333"}, {"lat": "-21.5166667", "city": "Pon\u00e9o", "lon": "165.5166667"}, {"lat": "-21.0833333", "city": "Pon\u00e9rihouen", "lon": "165.4"}, {"lat": "-21.0833333", "city": "Poneriuen", "lon": "165.4"}, {"lat": "-21.5", "city": "Ponibok", "lon": "167.9666667"}, {"lat": "-22.2166667", "city": "Pont-des-Fran\u00e7aise", "lon": "166.4833333"}, {"lat": "-22.2166667", "city": "Pont des Fran\u00e7ais", "lon": "166.4833333"}, {"lat": "-21.8333333", "city": "Popid\u00e9ry", "lon": "165.85"}, {"lat": "-21.1833333", "city": "P\u00f4", "lon": "165.3833333"}, {"lat": "-21.3166667", "city": "Poro", "lon": "165.6333333"}, {"lat": "-22.2666667", "city": "Port de France", "lon": "166.45"}, {"lat": "-20.4833333", "city": "Port Paagoum\u00e8ne", "lon": "164.1833333"}, {"lat": "-21.5166667", "city": "Port Sa\u00efd", "lon": "167.9"}, {"lat": "-21.45", "city": "Poth\u00e9", "lon": "165.4833333"}, {"lat": "-20.5166667", "city": "Pou\u00e9badou", "lon": "164.55"}, {"lat": "-20.4", "city": "Pou\u00e9bo", "lon": "164.5666667"}, {"lat": "-20.3666667", "city": "Pouedjane Maladj", "lon": "164.2"}, {"lat": "-20.8166667", "city": "Pou\u00e9 Kou\u00e9", "lon": "164.4833333"}, {"lat": "-21.1333333", "city": "Pouembout", "lon": "164.9"}, {"lat": "-20.7166667", "city": "Pouendiap", "lon": "164.9"}, {"lat": "-20.6833333", "city": "Pou\u00e9n\u00e9", "lon": "164.4833333"}, {"lat": "-21.5166667", "city": "Pou\u00e9o", "lon": "165.5166667"}, {"lat": "-20.7833333", "city": "Pou\u00e9pa\u00ef", "lon": "164.8"}, {"lat": "-20.6833333", "city": "Pouiembeng", "lon": "164.8833333"}, {"lat": "-20.8333333", "city": "Pouiou", "lon": "165.25"}, {"lat": "-20.2333333", "city": "Poume", "lon": "164.0166667"}, {"lat": "-20.2333333", "city": "Poum-Plage", "lon": "164.0333333"}, {"lat": "-20.2333333", "city": "Poum", "lon": "164.0166667"}, {"lat": "-20.2333333", "city": "Poum-Titch", "lon": "164.0166667"}, {"lat": "-21.35", "city": "Poya", "lon": "165.15"}, {"lat": "-22.3166667", "city": "Prony", "lon": "166.8166667"}, {"lat": "-20.4", "city": "Pu\u00e9bo", "lon": "164.5666667"}, {"lat": "-21.1333333", "city": "Puembut", "lon": "164.9"}, {"lat": "-20.2333333", "city": "Pum", "lon": "164.0166667"}, {"lat": "-21.0833333", "city": "Punereuin", "lon": "165.4"}, {"lat": "-21.8", "city": "Quameni", "lon": "165.9666667"}, {"lat": "-22.6", "city": "Quameo", "lon": "167.4333333"}, {"lat": "-21.4833333", "city": "Rawa", "lon": "167.9833333"}, {"lat": "-21.3833333", "city": "Rho", "lon": "167.8666667"}, {"lat": "-21.3", "city": "Roibahon", "lon": "165.5833333"}, {"lat": "-21.4666667", "city": "Ro\u00ef", "lon": "167.95"}, {"lat": "-21.3833333", "city": "R\u00f4", "lon": "167.8666667"}, {"lat": "-21.5333333", "city": "Ru\u00e8te", "lon": "167.9"}, {"lat": "-20.3833333", "city": "Saint-Adolphe", "lon": "164.5666667"}, {"lat": "-20.3166667", "city": "Saint-Denis", "lon": "164.5"}, {"lat": "-20.4333333", "city": "Sainte-Anne", "lon": "164.45"}, {"lat": "-20.3333333", "city": "Sainte-Marie", "lon": "164.5166667"}, {"lat": "-20.95", "city": "Sainte-Th\u00e9r\u00e8se", "lon": "165.2333333"}, {"lat": "-20.3833333", "city": "Saint-Ferdinand", "lon": "164.4166667"}, {"lat": "-20.4333333", "city": "Saint-Fran\u00e7ois", "lon": "164.4166667"}, {"lat": "-20.65", "city": "Saint-Gabrielee", "lon": "166.5833333"}, {"lat": "-20.3333333", "city": "Saint-Gabriel", "lon": "164.5166667"}, {"lat": "-20.4333333", "city": "Saint-Jean-Baptiste", "lon": "164.4333333"}, {"lat": "-20.4333333", "city": "Saint-Joachim", "lon": "164.45"}, {"lat": "-20.4", "city": "Saint-Joseph", "lon": "164.5666667"}, {"lat": "-20.9", "city": "Saint-L\u00e9onard", "lon": "165.2333333"}, {"lat": "-20.3666667", "city": "Saint-Louis", "lon": "164.5666667"}, {"lat": "-20.4333333", "city": "Saint-Michel", "lon": "164.4333333"}, {"lat": "-20.35", "city": "Saint-Paul", "lon": "164.5333333"}, {"lat": "-21.6166667", "city": "Saint-Philippe II", "lon": "166.2333333"}, {"lat": "-21.6333333", "city": "Saint-Philippe I", "lon": "166.2"}, {"lat": "-20.4333333", "city": "Saint-Pierre", "lon": "164.4333333"}, {"lat": "-21.7", "city": "Saint-Roch", "lon": "166.4"}, {"lat": "-20.4666667", "city": "Saint-Thomas", "lon": "166.65"}, {"lat": "-22.0833333", "city": "Saint-Vincent", "lon": "166.2833333"}, {"lat": "-21.1", "city": "Saint-Yves", "lon": "165.3"}, {"lat": "-21.65", "city": "Saram\u00e9a", "lon": "165.85"}, {"lat": "-21.65", "city": "Sarram\u00e9a", "lon": "165.85"}, {"lat": "-20.7833333", "city": "Shepenehe", "lon": "167.15"}, {"lat": "-20.7833333", "city": "Shoup", "lon": "167.2666667"}, {"lat": "-21.4666667", "city": "Shuane", "lon": "167.9666667"}, {"lat": "-20.7666667", "city": "Siloam", "lon": "167.1166667"}, {"lat": "-20.7333333", "city": "Station Castex", "lon": "164.8666667"}, {"lat": "-21.4666667", "city": "Station de Beaupr\u00e9", "lon": "165.1833333"}, {"lat": "-21.3", "city": "Station de Mu\u00e9o", "lon": "165.0166667"}, {"lat": "-21.0166667", "city": "Station de Ta", "lon": "164.7166667"}, {"lat": "-21.4666667", "city": "Station Ouan\u00e9ko", "lon": "165.1666667"}, {"lat": "-20.0166667", "city": "Taanl\u00f4", "lon": "163.9333333"}, {"lat": "-21.55", "city": "Tadine", "lon": "167.8833333"}, {"lat": "-21.55", "city": "Tadinou", "lon": "167.8833333"}, {"lat": "-21.55", "city": "Tadinu", "lon": "167.8833333"}, {"lat": "-20.7833333", "city": "Ta\u00eft\u00e9", "lon": "165.0833333"}, {"lat": "-20.4666667", "city": "Takedji", "lon": "166.6"}, {"lat": "-21.45", "city": "Taod\u00e9", "lon": "167.9166667"}, {"lat": "-20.85", "city": "Taom", "lon": "164.55"}, {"lat": "-20.55", "city": "Tao", "lon": "164.8"}, {"lat": "-21.5166667", "city": "Taradi", "lon": "165.9166667"}, {"lat": "-20.3666667", "city": "Tarap", "lon": "164.45"}, {"lat": "-21.2166667", "city": "Tarbeville", "lon": "164.8666667"}, {"lat": "-21.5", "city": "Tawa\u00efn\u00e8dre", "lon": "168.0833333"}, {"lat": "-21.0333333", "city": "Tchamba", "lon": "165.2833333"}, {"lat": "-20.4166667", "city": "Tchambouenne", "lon": "164.6"}, {"lat": "-20.05", "city": "Tchaul\u00e9", "lon": "163.8166667"}, {"lat": "-20.7333333", "city": "T\u00e9ganpa\u00efk", "lon": "165.0666667"}, {"lat": "-20.9", "city": "Temaio", "lon": "164.6833333"}, {"lat": "-20.9", "city": "T\u00e9mala", "lon": "164.6833333"}, {"lat": "-20.5333333", "city": "T\u00e9m\u00e9line", "lon": "164.5666667"}, {"lat": "-21.4", "city": "Tenane", "lon": "167.9"}, {"lat": "-21.55", "city": "Tenda", "lon": "166.0333333"}, {"lat": "-20.7166667", "city": "Tendo", "lon": "164.8166667"}, {"lat": "-20.6666667", "city": "T\u00e9nem", "lon": "164.9333333"}, {"lat": "-20.55", "city": "Tenja\u00ef", "lon": "164.2666667"}, {"lat": "-20.4", "city": "T\u00e9outa", "lon": "166.6166667"}, {"lat": "-21.7166667", "city": "Thia", "lon": "165.8"}, {"lat": "-21.6166667", "city": "Thio", "lon": "166.2166667"}, {"lat": "-21.4", "city": "Thogone", "lon": "167.9"}, {"lat": "-20.6166667", "city": "Thonon", "lon": "164.4666667"}, {"lat": "-21.0166667", "city": "Thuaha\u00efk", "lon": "167.2833333"}, {"lat": "-21.4833333", "city": "Thum", "lon": "167.9"}, {"lat": "-20.1333333", "city": "Tiabet", "lon": "164.0166667"}, {"lat": "-21.0", "city": "Tiakana", "lon": "164.8833333"}, {"lat": "-21.0166667", "city": "Tiamou", "lon": "164.8833333"}, {"lat": "-21.0", "city": "Tiaou\u00e9", "lon": "164.9166667"}, {"lat": "-20.9", "city": "Tiaou-Tiwaka", "lon": "165.2"}, {"lat": "-22.1666667", "city": "Tiar\u00e9", "lon": "166.2833333"}, {"lat": "-20.25", "city": "Tiari", "lon": "164.35"}, {"lat": "-21.7166667", "city": "Tia", "lon": "165.8"}, {"lat": "-20.9333333", "city": "Tibarama", "lon": "165.3833333"}, {"lat": "-20.45", "city": "Ti\u00e9baghi", "lon": "164.2166667"}, {"lat": "-20.7666667", "city": "Tiendanite", "lon": "164.9"}, {"lat": "-20.9333333", "city": "Ti\u00e9ta", "lon": "164.7333333"}, {"lat": "-20.9333333", "city": "Ti\u00e9t\u00e9", "lon": "165.3"}, {"lat": "-20.1166667", "city": "Ti\u00e9", "lon": "163.9833333"}, {"lat": "-20.9", "city": "Ti\u00e9ti", "lon": "165.2833333"}, {"lat": "-20.6666667", "city": "Tilougne", "lon": "164.9333333"}, {"lat": "-20.55", "city": "Tilwit", "lon": "164.4666667"}, {"lat": "-22.1333333", "city": "Timbia", "lon": "166.2166667"}, {"lat": "-20.4333333", "city": "Timoth\u00e9e", "lon": "164.4166667"}, {"lat": "-21.65", "city": "Tind\u00e9a", "lon": "165.7333333"}, {"lat": "-20.7166667", "city": "Tindo", "lon": "164.8166667"}, {"lat": "-20.7333333", "city": "Tingeting", "lon": "167.2666667"}, {"lat": "-20.7666667", "city": "Tinipp", "lon": "164.45"}, {"lat": "-20.7666667", "city": "Tinip", "lon": "164.45"}, {"lat": "-20.8166667", "city": "Tiol\u00e9", "lon": "167.25"}, {"lat": "-20.8", "city": "Tioua\u00e9", "lon": "165.15"}, {"lat": "-20.7333333", "city": "Tiouamak", "lon": "164.9166667"}, {"lat": "-20.7333333", "city": "Tiouand\u00e9", "lon": "165.0333333"}, {"lat": "-20.7333333", "city": "Tipindj\u00e9", "lon": "165.0"}, {"lat": "-20.7833333", "city": "Tiponite", "lon": "165.1833333"}, {"lat": "-20.9", "city": "Tiwaka", "lon": "165.2166667"}, {"lat": "-21.55", "city": "Todine", "lon": "167.8833333"}, {"lat": "-21.4833333", "city": "Toen", "lon": "167.85"}, {"lat": "-21.9666667", "city": "Tomo", "lon": "166.1333333"}, {"lat": "-20.7333333", "city": "Tonga", "lon": "166.4333333"}, {"lat": "-22.1833333", "city": "Tonghou\u00e9", "lon": "166.4833333"}, {"lat": "-22.1833333", "city": "Tongoue", "lon": "166.4833333"}, {"lat": "-22.1333333", "city": "Tongouin", "lon": "166.2166667"}, {"lat": "-20.55", "city": "Tonlon", "lon": "164.2666667"}, {"lat": "-22.1833333", "city": "Touaourou", "lon": "166.9666667"}, {"lat": "-20.7833333", "city": "Touho", "lon": "165.2333333"}, {"lat": "-21.0833333", "city": "Toul", "lon": "167.4166667"}, {"lat": "-20.9333333", "city": "Trapour", "lon": "167.3166667"}, {"lat": "-20.6833333", "city": "Tr\u00e9gon", "lon": "164.3833333"}, {"lat": "-20.65", "city": "Troulala", "lon": "164.3666667"}, {"lat": "-21.5333333", "city": "Tsendia", "lon": "166.0333333"}, {"lat": "-20.7833333", "city": "Tuho", "lon": "165.2333333"}, {"lat": "-20.65", "city": "Tunney", "lon": "164.3666667"}, {"lat": "-20.7833333", "city": "Tuo", "lon": "165.2333333"}, {"lat": "-21.2666667", "city": "T\u00fb", "lon": "165.5833333"}, {"lat": "-20.8333333", "city": "Uaco", "lon": "164.4666667"}, {"lat": "-20.8833333", "city": "Uagap", "lon": "165.2666667"}, {"lat": "-19.6833333", "city": "Uala", "lon": "163.65"}, {"lat": "-21.8", "city": "Uam\u00e9ni", "lon": "165.9666667"}, {"lat": "-22.5666667", "city": "Uapan", "lon": "167.45"}, {"lat": "-21.6", "city": "Uapao", "lon": "167.9333333"}, {"lat": "-22.4433333", "city": "Uara", "lon": "166.8366667"}, {"lat": "-20.4333333", "city": "Ubatche", "lon": "164.6333333"}, {"lat": "-20.4333333", "city": "Ubati", "lon": "164.6333333"}, {"lat": "-20.3166667", "city": "Uegoa", "lon": "164.5"}, {"lat": "-22.6666667", "city": "Upuaite", "lon": "167.4833333"}, {"lat": "-20.8333333", "city": "Usine", "lon": "164.4666667"}, {"lat": "-20.45", "city": "Uv\u00e9a", "lon": "166.6"}, {"lat": "-22.2833333", "city": "Vall\u00e9e des Colons", "lon": "166.45"}, {"lat": "-22.2666667", "city": "Vall\u00e9e du G\u00e9nie", "lon": "166.45"}, {"lat": "-22.2666667", "city": "Vall\u00e9e du Tir", "lon": "166.45"}, {"lat": "-20.9666667", "city": "Vall\u00e9e", "lon": "165.35"}, {"lat": "-22.6666667", "city": "Vao", "lon": "167.4833333"}, {"lat": "-20.7666667", "city": "Vieux-Touho", "lon": "165.15"}, {"lat": "-20.7666667", "city": "Vieux Tuho", "lon": "165.15"}, {"lat": "-20.9666667", "city": "Voh", "lon": "164.7"}, {"lat": "-21.6", "city": "Wabao", "lon": "167.9333333"}, {"lat": "-21.4666667", "city": "Wacamadra", "lon": "168.0333333"}, {"lat": "-20.6", "city": "Wadila", "lon": "166.5666667"}, {"lat": "-20.6", "city": "Wadrilla", "lon": "166.5666667"}, {"lat": "-20.8833333", "city": "Wagap", "lon": "165.2666667"}, {"lat": "-22.1666667", "city": "Waho", "lon": "166.95"}, {"lat": "-20.6833333", "city": "Wakat", "lon": "166.5333333"}, {"lat": "-21.45", "city": "Wakon\u00e9", "lon": "168.1"}, {"lat": "-21.4333333", "city": "Wakuarori", "lon": "167.9"}, {"lat": "-19.7166667", "city": "Wala", "lon": "163.6333333"}, {"lat": "-20.5666667", "city": "Wanap", "lon": "164.2666667"}, {"lat": "-22.5666667", "city": "Wapan", "lon": "167.45"}, {"lat": "-21.2666667", "city": "Wara", "lon": "165.6"}, {"lat": "-20.65", "city": "Wassadieuhu", "lon": "166.55"}, {"lat": "-21.0", "city": "Wassagne", "lon": "167.3833333"}, {"lat": "-20.6333333", "city": "Watahu", "lon": "166.55"}, {"lat": "-19.6666667", "city": "W\u00e9a", "lon": "163.65"}, {"lat": "-20.9833333", "city": "W\u00e9doumel", "lon": "167.1166667"}, {"lat": "-20.45", "city": "Wen\u00e9ki", "lon": "166.6166667"}, {"lat": "-20.65", "city": "Wengh\u00e9", "lon": "166.55"}, {"lat": "-20.9", "city": "W\u00e9", "lon": "167.2666667"}, {"lat": "-21.5333333", "city": "Winikuy\u00e9", "lon": "167.8833333"}, {"lat": "-21.0833333", "city": "Wiwatoul", "lon": "167.35"}, {"lat": "-22.2", "city": "Yahou\u00e9", "lon": "166.5"}, {"lat": "-20.45", "city": "Yamb\u00e9", "lon": "164.65"}, {"lat": "-22.15", "city": "Yat\u00e9-Barrage", "lon": "166.8833333"}, {"lat": "-22.15", "city": "Yat\u00e9-Village", "lon": "166.9"}, {"lat": "-22.15", "city": "Yat\u00e9", "lon": "166.9"}, {"lat": "-20.6833333", "city": "Yengen", "lon": "164.9333333"}, {"lat": "-20.1", "city": "Yengh\u00e9bane", "lon": "163.9666667"}, {"lat": "-21.0333333", "city": "Zoangani", "lon": "167.4166667"}, {"lat": "-21.05", "city": "Zoze", "lon": "167.4333333"}]}}